COPYRIGHT
MANIFEST.in
setup.cfg
setup.py
docs/Makefile
docs/api_docs.rst
docs/conf.py
docs/eurostat.rst
docs/index.rst
docs/make.bat
docs/unstats.rst
docs/utilities.rst
ukgov/__init__.py
ukgov/hmt/__init__.py
ukgov/hmt/cra/__init__.py
ukgov/reference/__init__.py
ukgov/reference/time.py
ukgov_treasury_cra.egg-info/PKG-INFO
ukgov_treasury_cra.egg-info/SOURCES.txt
ukgov_treasury_cra.egg-info/datapkg_index.txt
ukgov_treasury_cra.egg-info/datapkg_sources.spec
ukgov_treasury_cra.egg-info/dependency_links.txt
ukgov_treasury_cra.egg-info/entry_points.txt
ukgov_treasury_cra.egg-info/not-zip-safe
ukgov_treasury_cra.egg-info/requires.txt
ukgov_treasury_cra.egg-info/top_level.txt