Metadata-Version: 1.0
Name: ukgov-treasury-cra
Version: 0.1
Summary: HM Treasury's Country and Regional Analysis
Home-page: http://purl.org/okfn/dataset/cra/2009
Author: Open Knowledge Foundation
Author-email: okfn-help@lists.okfn.org
License: AGPL
Keywords: cra uk
Platform: UNKNOWN
Classifier: Development Status :: 3 - Alpha
Classifier: Environment :: Console
Classifier: Environment :: Web Environment
Classifier: Framework :: Paste
Classifier: Intended Audience :: Developers
Classifier: Intended Audience :: Information Technology
Classifier: License :: OSI Approved :: GNU Affero General Public License v3
Classifier: Operating System :: POSIX
Classifier: Programming Language :: Python :: 2.6
Classifier: Topic :: Internet
Classifier: Topic :: Software Development :: Libraries :: Python Modules
